rrta/__init__.py
rrta/adapter.py
rrta/client.py
rrta/exceptions.py
rrta/models/__init__.py
rrta/models/messages.py
rrta/models/result.py
rrta/models/route.py
rrta/models/routedetails.py
rrta/models/stopdepartures.py
rrta/models/stops.py
rrta/models/vehicles.py
rrta-0.1.dist-info/LICENSE
rrta-0.1.dist-info/METADATA
rrta-0.1.dist-info/WHEEL
rrta-0.1.dist-info/top_level.txt
rrta-0.1.dist-info/RECORD
