Metadata-Version: 2.1
Name: rrta
Version: 0.1
Summary: Python wrapper for the RRTA (MyStop) REST API.
Author-email: Nate Shoffner <nate.shoffner@gmail.com>
Project-URL: Homepage, https://github.com/NateShoffner/python-rrta
Project-URL: Bug Tracker, https://github.com/NateShoffner/python-rrta/issues
Keywords: rrta,lancaster
Classifier: Programming Language :: Python :: 3
Classifier: License :: OSI Approved :: MIT License
Classifier: Operating System :: OS Independent
Requires-Python: >=3.9
License-File: LICENSE
Requires-Dist: aiohttp
